mucalla/__init__.py
mucalla/call.py
mucalla/constants.py
mucalla/exceptions.py
mucalla/loggers.py
mucalla/multicall.py
mucalla/signature.py
mucalla/utils.py
mucalla-0.0.2.dist-info/WHEEL
mucalla-0.0.2.dist-info/METADATA
mucalla-0.0.2.dist-info/RECORD
